django_p/__init__.py
django_p/admin.py
django_p/models.py
django_p/pipeline.py
django_p/tests.py
django_p/util.py
django_p/views.py
django_p/migrations/0001_initial.py
django_p/migrations/0002_auto_20160529_1026.py
django_p/migrations/0003_auto_20160529_1027.py
django_p/migrations/0004_auto_20160529_1059.py
django_p/migrations/0005_auto_20160602_0908.py
django_p/migrations/0006_auto_20160602_1413.py
django_p/migrations/__init__.py
django_p-0.1.dist-info/DESCRIPTION.rst
django_p-0.1.dist-info/METADATA
django_p-0.1.dist-info/RECORD
django_p-0.1.dist-info/WHEEL
django_p-0.1.dist-info/metadata.json
django_p-0.1.dist-info/top_level.txt
